{
  "nowPlaying": [
    {
      "title": "Inside Out 2",
      "poster": "./assets/poster/insideout2.png",
      "trailer": "https://www.youtube.com/embed/LEjhY15eCx0",
      "synopsis": "Lorem ipsum dolor sit amet consectetur, adipisicing elit. Commodi accusamus tempora et eveniet architecto quidem maxime ab, cupiditate deserunt possimus pariatur, mollitia assumenda at magni laudantium nemo voluptatum dicta voluptates fugit, voluptatibus hic! Perferendis quod dignissimos minus laudantium odio suscipit.",
      "duration": "150 min",
      "rate": 5,
      "age": "13+",
      "schedule": [
        {
          "date": "2024-06-25",
          "times": ["14:00", "17:00", "20:00"]
        },
        {
          "date": "2024-06-26",
          "times": ["12:00", "15:00", "18:00"]
        }
      ],
      "reviews": [
        {
          "name": "Kanda Yow",
          "rating": 5,
          "comment": "Filmnya keren abies yoww, jadi gasabar untuk series selanjutnya!"
        },
        {
          "name": "Pocy",
          "rating": 4,
          "comment": "Very good, will come again."
        },
        {
          "name": "Leann",
          "rating": 2,
          "comment": "Just OK and need room for improvement."
        }
      ]
    },
    {
      "title": "DILAN 1983 WO AI NI",
      "poster": "./assets/poster/dilan.png",
      "trailer": "https://www.youtube.com/watch?v=trailer1",
      "synopsis": "Synopsis for Inside Out 2",
      "duration": "1h 35m"
    },
    {
      "title": "HOW TO MAKE MILLIONS BEFORE GRANDMA DIES",
      "poster": "./assets/poster/grandma.png",
      "trailer": "https://www.youtube.com/watch?v=trailer1",
      "synopsis": "Synopsis for Inside Out 2",
      "duration": "1h 35m"
    },
    {
      "title": "THE GARFIELD MOVIE",
      "poster": "./assets/poster/garfield.png",
      "trailer": "https://www.youtube.com/watch?v=trailer1",
      "synopsis": "Synopsis for Inside Out 2",
      "duration": "1h 35m"
    },
    {
      "title": "HAIKYU!! THE DUMPSTER BATTLE",
      "poster": "./assets/poster/haikyu.png",
      "trailer": "https://www.youtube.com/watch?v=trailer1",
      "synopsis": "Synopsis for Inside Out 2",
      "duration": "1h 35m"
    },
    {
      "title": "PAKU TANAH JAWA",
      "poster": "./assets/poster/pakutanahjawa.png",
      "trailer": "https://www.youtube.com/watch?v=trailer1",
      "synopsis": "Synopsis for Inside Out 2",
      "duration": "1h 35m"
    },
    {
      "title": "THE STRANGERS: CHAPTER 1",
      "poster": "./assets/poster/strangers.png",
      "trailer": "https://www.youtube.com/watch?v=trailer1",
      "synopsis": "Synopsis for Inside Out 2",
      "duration": "1h 35m"
    },
    {
      "title": "DETECTIVE CONAN VS KID THE PHANTOM THIEF",
      "poster": "./assets/poster/conan.png",
      "trailer": "https://www.youtube.com/watch?v=trailer1",
      "synopsis": "Synopsis for Inside Out 2",
      "duration": "1h 35m"
    },
    {
      "title": "THE PLOT",
      "poster": "./assets/poster/theplot.png",
      "trailer": "https://www.youtube.com/watch?v=trailer1",
      "synopsis": "Synopsis for Inside Out 2",
      "duration": "1h 35m"
    },
    {
      "title": "IPAR ADALAH MAUT",
      "poster": "./assets/poster/ipar.png",
      "trailer": "https://www.youtube.com/watch?v=trailer1",
      "synopsis": "Synopsis for Inside Out 2",
      "duration": "1h 35m"
    },
    {
      "title": "SENGKOLO: MALAM SATU SURO",
      "poster": "./assets/poster/sengkolo.png",
      "trailer": "https://www.youtube.com/watch?v=trailer1",
      "synopsis": "Synopsis for Inside Out 2",
      "duration": "1h 35m"
    }
  ],
  "upcoming": [
    {
      "title": "The Exorcism",
      "poster": "./assets/poster/exorcism.jpg",
      "trailer": "https://www.youtube.com/embed/trailer4",
      "synopsis": "Synopsis for The Exorcism",
      "duration": "105 min",
      "rating": 4,
      "age": "18+",
      "schedule": []
    },
    {
      "title": "Despicable Me 4",
      "poster": "./assets/poster/despicableme4.jpg",
      "trailer": "https://www.youtube.com/watch?v=trailer4",
      "synopsis": "Synopsis for Despicable Me 4",
      "duration": "1h 50m"
    },
    {
      "title": "FROZEN 3",
      "poster": "./assets/poster/frozen.png",
      "trailer": "https://www.youtube.com/watch?v=trailer1",
      "synopsis": "Synopsis for Inside Out 2",
      "duration": "1h 35m"
    },
    {
      "title": "DEADPOOL VS WOLVERINE",
      "poster": "./assets/poster/deadpool.jpg",
      "trailer": "https://www.youtube.com/watch?v=trailer1",
      "synopsis": "Synopsis for Inside Out 2",
      "duration": "1h 35m"
    },
    {
      "title": "MY BOO",
      "poster": "./assets/poster/myboo.png",
      "trailer": "https://www.youtube.com/watch?v=trailer1",
      "synopsis": "Synopsis for Inside Out 2",
      "duration": "1h 35m"
    }
  ]
}
